runat/__init__.py
runat/main.py
runat-1.0.2.dist-info/LICENSE
runat-1.0.2.dist-info/METADATA
runat-1.0.2.dist-info/WHEEL
runat-1.0.2.dist-info/entry_points.txt
runat-1.0.2.dist-info/top_level.txt
runat-1.0.2.dist-info/RECORD
