Metadata-Version: 2.1
Name: runat
Version: 1.0.2
Summary: Cli like cron, to run task a specific time
Home-page: https://github.com/alivx/runat
Author: Ali Saleh Baker
Author-email: alivxlive@gmail.com
License: GNU
Keywords: cron,at,timer,time,cli
Platform: UNKNOWN
Requires-Dist: click (==8.1.3)
